{
  "type": "FeatureCollection",
  "features": [
    {
      "type": "Feature",
      "properties": {
        "id": 37330450,
        "railway": "switch"
      },
      "geometry": {
        "type": "Point",
        "coordinates": [
          -76.6547413,
          39.4929347
        ]
      }
    },
    {
      "type": "Feature",
      "properties": {
        "id": 37370274,
        "railway": "switch"
      },
      "geometry": {
        "type": "Point",
        "coordinates": [
          -76.6612983,
          39.4835839
        ]
      }
    },
    {
      "type": "Feature",
      "properties": {
        "id": 37570545,
        "railway": "switch"
      },
      "geometry": {
        "type": "Point",
        "coordinates": [
          -76.6283964,
          39.434746
        ]
      }
    },
    {
      "type": "Feature",
      "properties": {
        "id": 37570574,
        "railway": "switch"
      },
      "geometry": {
        "type": "Point",
        "coordinates": [
          -76.6403498,
          39.4576987
        ]
      }
    },
    {
      "type": "Feature",
      "properties": {
        "id": 37571060,
        "railway": "switch"
      },
      "geometry": {
        "type": "Point",
        "coordinates": [
          -76.6424364,
          39.4609943
        ]
      }
    },
    {
      "type": "Feature",
      "properties": {
        "id": 37571470,
        "railway": "switch"
      },
      "geometry": {
        "type": "Point",
        "coordinates": [
          -76.6526755,
          39.3724665
        ]
      }
    },
    {
      "type": "Feature",
      "properties": {
        "id": 49415327,
        "railway": "switch"
      },
      "geometry": {
        "type": "Point",
        "coordinates": [
          -76.6480285,
          39.3445276
        ]
      }
    },
    {
      "type": "Feature",
      "properties": {
        "id": 49423503,
        "railway": "switch"
      },
      "geometry": {
        "type": "Point",
        "coordinates": [
          -76.6331137,
          39.2602484
        ]
      }
    },
    {
      "type": "Feature",
      "properties": {
        "id": 49517283,
        "railway": "switch"
      },
      "geometry": {
        "type": "Point",
        "coordinates": [
          -76.6468575,
          39.3360214
        ]
      }
    },
    {
      "type": "Feature",
      "properties": {
        "id": 49517362,
        "railway": "switch"
      },
      "geometry": {
        "type": "Point",
        "coordinates": [
          -76.6297327,
          39.3200178
        ]
      }
    },
    {
      "type": "Feature",
      "properties": {
        "id": 49517366,
        "railway": "switch"
      },
      "geometry": {
        "type": "Point",
        "coordinates": [
          -76.628443,
          39.3184234
        ]
      }
    },
    {
      "type": "Feature",
      "properties": {
        "id": 49518672,
        "railway": "switch"
      },
      "geometry": {
        "type": "Point",
        "coordinates": [
          -76.6527366,
          39.3722281
        ]
      }
    },
    {
      "type": "Feature",
      "properties": {
        "id": 102583330,
        "railway": "switch"
      },
      "geometry": {
        "type": "Point",
        "coordinates": [
          -76.6556754,
          39.199316
        ]
      }
    },
    {
      "type": "Feature",
      "properties": {
        "id": 256525880,
        "railway": "switch"
      },
      "geometry": {
        "type": "Point",
        "coordinates": [
          -76.6199547,
          39.3079602
        ]
      }
    },
    {
      "type": "Feature",
      "properties": {
        "id": 265016624,
        "railway": "switch"
      },
      "geometry": {
        "type": "Point",
        "coordinates": [
          -76.657619,
          39.1941936
        ]
      }
    },
    {
      "type": "Feature",
      "properties": {
        "id": 265016633,
        "railway": "switch"
      },
      "geometry": {
        "type": "Point",
        "coordinates": [
          -76.6543943,
          39.1974019
        ]
      }
    },
    {
      "type": "Feature",
      "properties": {
        "id": 266637246,
        "railway": "switch"
      },
      "geometry": {
        "type": "Point",
        "coordinates": [
          -76.6220633,
          39.3110546
        ]
      }
    },
    {
      "type": "Feature",
      "properties": {
        "id": 266637249,
        "railway": "switch"
      },
      "geometry": {
        "type": "Point",
        "coordinates": [
          -76.6232738,
          39.3126717
        ]
      }
    },
    {
      "type": "Feature",
      "properties": {
        "id": 267924300,
        "railway": "switch"
      },
      "geometry": {
        "type": "Point",
        "coordinates": [
          -76.619219,
          39.2813082
        ]
      }
    },
    {
      "type": "Feature",
      "properties": {
        "id": 267924304,
        "railway": "switch"
      },
      "geometry": {
        "type": "Point",
        "coordinates": [
          -76.6195455,
          39.2842575
        ]
      }
    },
    {
      "type": "Feature",
      "properties": {
        "id": 678855178,
        "railway": "switch"
      },
      "geometry": {
        "type": "Point",
        "coordinates": [
          -76.6346628,
          39.4480045
        ]
      }
    },
    {
      "type": "Feature",
      "properties": {
        "id": 832325423,
        "railway": "switch"
      },
      "geometry": {
        "type": "Point",
        "coordinates": [
          -76.6236218,
          39.3129776
        ]
      }
    },
    {
      "type": "Feature",
      "properties": {
        "id": 844179110,
        "railway": "switch"
      },
      "geometry": {
        "type": "Point",
        "coordinates": [
          -76.6400007,
          39.4572604
        ]
      }
    },
    {
      "type": "Feature",
      "properties": {
        "id": 844179175,
        "railway": "switch"
      },
      "geometry": {
        "type": "Point",
        "coordinates": [
          -76.6446936,
          39.4740304
        ]
      }
    },
    {
      "type": "Feature",
      "properties": {
        "id": 844179179,
        "railway": "switch"
      },
      "geometry": {
        "type": "Point",
        "coordinates": [
          -76.6343618,
          39.4475377
        ]
      }
    },
    {
      "type": "Feature",
      "properties": {
        "id": 844179221,
        "railway": "switch"
      },
      "geometry": {
        "type": "Point",
        "coordinates": [
          -76.6426658,
          39.4615147
        ]
      }
    },
    {
      "type": "Feature",
      "properties": {
        "id": 844179250,
        "railway": "switch"
      },
      "geometry": {
        "type": "Point",
        "coordinates": [
          -76.6419771,
          39.4601433
        ]
      }
    },
    {
      "type": "Feature",
      "properties": {
        "id": 844179345,
        "railway": "switch"
      },
      "geometry": {
        "type": "Point",
        "coordinates": [
          -76.6447077,
          39.4735982
        ]
      }
    },
    {
      "type": "Feature",
      "properties": {
        "id": 844179392,
        "railway": "switch"
      },
      "geometry": {
        "type": "Point",
        "coordinates": [
          -76.6399106,
          39.4570469
        ]
      }
    },
    {
      "type": "Feature",
      "properties": {
        "id": 844224833,
        "railway": "switch"
      },
      "geometry": {
        "type": "Point",
        "coordinates": [
          -76.6335487,
          39.4459461
        ]
      }
    },
    {
      "type": "Feature",
      "properties": {
        "id": 844224888,
        "railway": "switch"
      },
      "geometry": {
        "type": "Point",
        "coordinates": [
          -76.6381467,
          39.4178546
        ]
      }
    },
    {
      "type": "Feature",
      "properties": {
        "id": 844225056,
        "railway": "switch"
      },
      "geometry": {
        "type": "Point",
        "coordinates": [
          -76.6337845,
          39.4464715
        ]
      }
    },
    {
      "type": "Feature",
      "properties": {
        "id": 844225180,
        "railway": "switch"
      },
      "geometry": {
        "type": "Point",
        "coordinates": [
          -76.6376832,
          39.4182319
        ]
      }
    },
    {
      "type": "Feature",
      "properties": {
        "id": 844696246,
        "railway": "switch"
      },
      "geometry": {
        "type": "Point",
        "coordinates": [
          -76.6528234,
          39.3717116
        ]
      }
    },
    {
      "type": "Feature",
      "properties": {
        "id": 844696404,
        "railway": "switch"
      },
      "geometry": {
        "type": "Point",
        "coordinates": [
          -76.6474956,
          39.3372804
        ]
      }
    },
    {
      "type": "Feature",
      "properties": {
        "id": 844696406,
        "railway": "switch"
      },
      "geometry": {
        "type": "Point",
        "coordinates": [
          -76.6525024,
          39.3729697
        ]
      }
    },
    {
      "type": "Feature",
      "properties": {
        "id": 844696891,
        "railway": "switch"
      },
      "geometry": {
        "type": "Point",
        "coordinates": [
          -76.6465564,
          39.3355548
        ]
      }
    },
    {
      "type": "Feature",
      "properties": {
        "id": 844697117,
        "railway": "switch"
      },
      "geometry": {
        "type": "Point",
        "coordinates": [
          -76.6472767,
          39.3367898
        ]
      }
    },
    {
      "type": "Feature",
      "properties": {
        "id": 844811854,
        "railway": "switch"
      },
      "geometry": {
        "type": "Point",
        "coordinates": [
          -76.6234471,
          39.3128924
        ]
      }
    },
    {
      "type": "Feature",
      "properties": {
        "id": 844812205,
        "railway": "switch"
      },
      "geometry": {
        "type": "Point",
        "coordinates": [
          -76.6287637,
          39.3188883
        ]
      }
    },
    {
      "type": "Feature",
      "properties": {
        "id": 844812253,
        "railway": "switch"
      },
      "geometry": {
        "type": "Point",
        "coordinates": [
          -76.6301885,
          39.320651
        ]
      }
    },
    {
      "type": "Feature",
      "properties": {
        "id": 844812314,
        "railway": "switch"
      },
      "geometry": {
        "type": "Point",
        "coordinates": [
          -76.6235896,
          39.3130089
        ]
      }
    },
    {
      "type": "Feature",
      "properties": {
        "id": 844812394,
        "railway": "switch"
      },
      "geometry": {
        "type": "Point",
        "coordinates": [
          -76.629339,
          39.3195978
        ]
      }
    },
    {
      "type": "Feature",
      "properties": {
        "id": 844812426,
        "railway": "switch"
      },
      "geometry": {
        "type": "Point",
        "coordinates": [
          -76.6293223,
          39.3196599
        ]
      }
    },
    {
      "type": "Feature",
      "properties": {
        "id": 844812429,
        "railway": "switch"
      },
      "geometry": {
        "type": "Point",
        "coordinates": [
          -76.6199057,
          39.3079618
        ]
      }
    },
    {
      "type": "Feature",
      "properties": {
        "id": 844812453,
        "railway": "switch"
      },
      "geometry": {
        "type": "Point",
        "coordinates": [
          -76.6194212,
          39.30875
        ]
      }
    },
    {
      "type": "Feature",
      "properties": {
        "id": 844812486,
        "railway": "switch"
      },
      "geometry": {
        "type": "Point",
        "coordinates": [
          -76.6294988,
          39.3198764
        ]
      }
    },
    {
      "type": "Feature",
      "properties": {
        "id": 844812547,
        "railway": "switch"
      },
      "geometry": {
        "type": "Point",
        "coordinates": [
          -76.6223103,
          39.3114851
        ]
      }
    },
    {
      "type": "Feature",
      "properties": {
        "id": 844812871,
        "railway": "switch"
      },
      "geometry": {
        "type": "Point",
        "coordinates": [
          -76.6219413,
          39.3110896
        ]
      }
    },
    {
      "type": "Feature",
      "properties": {
        "id": 845910808,
        "operator": "Maryland Transit Administration",
        "operator:wikidata": "Q1863801",
        "railway": "switch"
      },
      "geometry": {
        "type": "Point",
        "coordinates": [
          -76.6193617,
          39.2847327
        ]
      }
    },
    {
      "type": "Feature",
      "properties": {
        "id": 845910931,
        "railway": "switch"
      },
      "geometry": {
        "type": "Point",
        "coordinates": [
          -76.6194677,
          39.2837985
        ]
      }
    },
    {
      "type": "Feature",
      "properties": {
        "id": 845911268,
        "railway": "switch"
      },
      "geometry": {
        "type": "Point",
        "coordinates": [
          -76.6193016,
          39.2818695
        ]
      }
    },
    {
      "type": "Feature",
      "properties": {
        "id": 845911280,
        "railway": "switch"
      },
      "geometry": {
        "type": "Point",
        "coordinates": [
          -76.6191808,
          39.2813653
        ]
      }
    },
    {
      "type": "Feature",
      "properties": {
        "id": 847727154,
        "railway": "switch"
      },
      "geometry": {
        "type": "Point",
        "coordinates": [
          -76.6201737,
          39.2784714
        ]
      }
    },
    {
      "type": "Feature",
      "properties": {
        "id": 847727216,
        "railway": "switch"
      },
      "geometry": {
        "type": "Point",
        "coordinates": [
          -76.6328039,
          39.260664
        ]
      }
    },
    {
      "type": "Feature",
      "properties": {
        "id": 847727230,
        "railway": "switch"
      },
      "geometry": {
        "type": "Point",
        "coordinates": [
          -76.6203927,
          39.2780484
        ]
      }
    },
    {
      "type": "Feature",
      "properties": {
        "id": 847727287,
        "railway": "switch"
      },
      "geometry": {
        "type": "Point",
        "coordinates": [
          -76.6326831,
          39.2608677
        ]
      }
    },
    {
      "type": "Feature",
      "properties": {
        "id": 847727339,
        "railway": "switch"
      },
      "geometry": {
        "type": "Point",
        "coordinates": [
          -76.6203467,
          39.2780323
        ]
      }
    },
    {
      "type": "Feature",
      "properties": {
        "id": 847727399,
        "railway": "switch"
      },
      "geometry": {
        "type": "Point",
        "coordinates": [
          -76.6201287,
          39.2784568
        ]
      }
    },
    {
      "type": "Feature",
      "properties": {
        "id": 847727423,
        "railway": "switch"
      },
      "geometry": {
        "type": "Point",
        "coordinates": [
          -76.6324778,
          39.2613003
        ]
      }
    },
    {
      "type": "Feature",
      "properties": {
        "id": 848279120,
        "railway": "switch"
      },
      "geometry": {
        "type": "Point",
        "coordinates": [
          -76.630543,
          39.2453532
        ]
      }
    },
    {
      "type": "Feature",
      "properties": {
        "id": 848279131,
        "railway": "switch"
      },
      "geometry": {
        "type": "Point",
        "coordinates": [
          -76.631538,
          39.2384314
        ]
      }
    },
    {
      "type": "Feature",
      "properties": {
        "id": 848279248,
        "railway": "switch"
      },
      "geometry": {
        "type": "Point",
        "coordinates": [
          -76.6317013,
          39.2379214
        ]
      }
    },
    {
      "type": "Feature",
      "properties": {
        "id": 848279251,
        "railway": "switch"
      },
      "geometry": {
        "type": "Point",
        "coordinates": [
          -76.6404513,
          39.2234942
        ]
      }
    },
    {
      "type": "Feature",
      "properties": {
        "id": 848279271,
        "railway": "switch"
      },
      "geometry": {
        "type": "Point",
        "coordinates": [
          -76.6318571,
          39.2375546
        ]
      }
    },
    {
      "type": "Feature",
      "properties": {
        "id": 848279302,
        "railway": "switch"
      },
      "geometry": {
        "type": "Point",
        "coordinates": [
          -76.6541587,
          39.1972543
        ]
      }
    },
    {
      "type": "Feature",
      "properties": {
        "id": 848279323,
        "railway": "switch"
      },
      "geometry": {
        "type": "Point",
        "coordinates": [
          -76.6332847,
          39.2485298
        ]
      }
    },
    {
      "type": "Feature",
      "properties": {
        "id": 848279328,
        "railway": "switch"
      },
      "geometry": {
        "type": "Point",
        "coordinates": [
          -76.6321081,
          39.2370866
        ]
      }
    },
    {
      "type": "Feature",
      "properties": {
        "id": 848279330,
        "railway": "switch"
      },
      "geometry": {
        "type": "Point",
        "coordinates": [
          -76.6556249,
          39.1993358
        ]
      }
    },
    {
      "type": "Feature",
      "properties": {
        "id": 848279331,
        "railway": "switch"
      },
      "geometry": {
        "type": "Point",
        "coordinates": [
          -76.6411213,
          39.2221559
        ]
      }
    },
    {
      "type": "Feature",
      "properties": {
        "id": 848279360,
        "railway": "switch"
      },
      "geometry": {
        "type": "Point",
        "coordinates": [
          -76.6406606,
          39.2229722
        ]
      }
    },
    {
      "type": "Feature",
      "properties": {
        "id": 848279393,
        "railway": "switch"
      },
      "geometry": {
        "type": "Point",
        "coordinates": [
          -76.6330013,
          39.2481189
        ]
      }
    },
    {
      "type": "Feature",
      "properties": {
        "id": 848279402,
        "railway": "switch"
      },
      "geometry": {
        "type": "Point",
        "coordinates": [
          -76.6553644,
          39.1988127
        ]
      }
    },
    {
      "type": "Feature",
      "properties": {
        "id": 848279436,
        "railway": "switch"
      },
      "geometry": {
        "type": "Point",
        "coordinates": [
          -76.655317,
          39.198831
        ]
      }
    },
    {
      "type": "Feature",
      "properties": {
        "id": 848279437,
        "railway": "switch"
      },
      "geometry": {
        "type": "Point",
        "coordinates": [
          -76.6408336,
          39.2226234
        ]
      }
    },
    {
      "type": "Feature",
      "properties": {
        "id": 848317909,
        "railway": "switch"
      },
      "geometry": {
        "type": "Point",
        "coordinates": [
          -76.6569581,
          39.1944746
        ]
      }
    },
    {
      "type": "Feature",
      "properties": {
        "id": 848317965,
        "railway": "switch"
      },
      "geometry": {
        "type": "Point",
        "coordinates": [
          -76.673119,
          39.1859475
        ]
      }
    },
    {
      "type": "Feature",
      "properties": {
        "id": 848317970,
        "railway": "switch"
      },
      "geometry": {
        "type": "Point",
        "coordinates": [
          -76.670912,
          39.1838195
        ]
      }
    },
    {
      "type": "Feature",
      "properties": {
        "id": 848317971,
        "railway": "switch"
      },
      "geometry": {
        "type": "Point",
        "coordinates": [
          -76.6563509,
          39.1946981
        ]
      }
    },
    {
      "type": "Feature",
      "properties": {
        "id": 848318013,
        "railway": "switch"
      },
      "geometry": {
        "type": "Point",
        "coordinates": [
          -76.6572085,
          39.1943665
        ]
      }
    },
    {
      "type": "Feature",
      "properties": {
        "id": 848318035,
        "railway": "switch"
      },
      "geometry": {
        "type": "Point",
        "coordinates": [
          -76.6577844,
          39.1940848
        ]
      }
    },
    {
      "type": "Feature",
      "properties": {
        "id": 850370891,
        "railway": "switch"
      },
      "geometry": {
        "type": "Point",
        "coordinates": [
          -76.6344425,
          39.1738909
        ]
      }
    },
    {
      "type": "Feature",
      "properties": {
        "id": 850371044,
        "railway": "switch"
      },
      "geometry": {
        "type": "Point",
        "coordinates": [
          -76.633491,
          39.1726486
        ]
      }
    },
    {
      "type": "Feature",
      "properties": {
        "id": 850371137,
        "railway": "switch"
      },
      "geometry": {
        "type": "Point",
        "coordinates": [
          -76.6341004,
          39.1733948
        ]
      }
    },
    {
      "type": "Feature",
      "properties": {
        "id": 850371366,
        "railway": "switch"
      },
      "geometry": {
        "type": "Point",
        "coordinates": [
          -76.6341384,
          39.1734499
        ]
      }
    },
    {
      "type": "Feature",
      "properties": {
        "id": 850371420,
        "railway": "switch"
      },
      "geometry": {
        "type": "Point",
        "coordinates": [
          -76.6339116,
          39.1731089
        ]
      }
    },
    {
      "type": "Feature",
      "properties": {
        "id": 7785824013,
        "railway": "switch"
      },
      "geometry": {
        "type": "Point",
        "coordinates": [
          -76.6228432,
          39.3122129
        ]
      }
    },
    {
      "type": "Feature",
      "properties": {
        "id": 7975207443,
        "railway": "switch"
      },
      "geometry": {
        "type": "Point",
        "coordinates": [
          -76.6367119,
          39.4189113
        ]
      }
    },
    {
      "type": "Feature",
      "properties": {
        "id": 7975207447,
        "railway": "switch"
      },
      "geometry": {
        "type": "Point",
        "coordinates": [
          -76.6363238,
          39.419144
        ]
      }
    }
  ]
}