{
  "type": "FeatureCollection",
  "generated": "2026-01-19T07:21:39.304Z",
  "source": "OpenStreetMap via Overpass API",
  "features": [
    {
      "type": "Feature",
      "properties": {
        "id": 1,
        "name": "Reservoir Yard Lead Track (from C Line)",
        "pointCount": 578
      },
      "geometry": {
        "type": "Polygon",
        "coordinates": [
          [
            [
              -71.1492711,
              42.3351233
            ],
            [
              -71.1476366,
              42.3351888
            ],
            [
              -71.1475666,
              42.3351939
            ],
            [
              -71.1471524,
              42.3352335
            ],
            [
              -71.1470731,
              42.3352442
            ],
            [
              -71.1445357,
              42.3357445
            ],
            [
              -71.1434555,
              42.3359867
            ],
            [
              -71.1530216,
              42.338216
            ],
            [
              -71.1535395,
              42.3380802
            ],
            [
              -71.1535436,
              42.3380445
            ],
            [
              -71.150483,
              42.3355751
            ],
            [
              -71.1504365,
              42.3355388
            ],
            [
              -71.1502739,
              42.3354299
            ],
            [
              -71.1502534,
              42.3354177
            ],
            [
              -71.1502281,
              42.3354058
            ],
            [
              -71.1502,
              42.3353955
            ],
            [
              -71.1499498,
              42.3353144
            ],
            [
              -71.1492711,
              42.3351233
            ]
          ]
        ]
      }
    },
    {
      "type": "Feature",
      "properties": {
        "id": 2,
        "name": "Green Line Brattle Loop",
        "pointCount": 75
      },
      "geometry": {
        "type": "Polygon",
        "coordinates": [
          [
            [
              -71.1168851,
              42.3536033
            ],
            [
              -71.1179447,
              42.354125
            ],
            [
              -71.1180437,
              42.3541698
            ],
            [
              -71.1181632,
              42.3542215
            ],
            [
              -71.1182879,
              42.3542706
            ],
            [
              -71.1185441,
              42.3543658
            ],
            [
              -71.1186624,
              42.3544045
            ],
            [
              -71.1196611,
              42.3547179
            ],
            [
              -71.1197809,
              42.3547452
            ],
            [
              -71.1199291,
              42.3547724
            ],
            [
              -71.1200691,
              42.3547955
            ],
            [
              -71.1199357,
              42.3545594
            ],
            [
              -71.1168851,
              42.3536033
            ]
          ]
        ]
      }
    },
    {
      "type": "Feature",
      "properties": {
        "id": 3,
        "name": "3rd Iron",
        "pointCount": 38
      },
      "geometry": {
        "type": "Polygon",
        "coordinates": [
          [
            [
              -71.1270237,
              42.3556926
            ],
            [
              -71.1271295,
              42.355744
            ],
            [
              -71.1287004,
              42.355999
            ],
            [
              -71.1288655,
              42.3560185
            ],
            [
              -71.1290274,
              42.356037
            ],
            [
              -71.1291281,
              42.3560456
            ],
            [
              -71.1307962,
              42.3561092
            ],
            [
              -71.1303289,
              42.3560141
            ],
            [
              -71.1302519,
              42.3559992
            ],
            [
              -71.1301571,
              42.3559855
            ],
            [
              -71.1270237,
              42.3556926
            ]
          ]
        ]
      }
    },
    {
      "type": "Feature",
      "properties": {
        "id": 4,
        "name": "B&A Westbound",
        "pointCount": 66
      },
      "geometry": {
        "type": "Polygon",
        "coordinates": [
          [
            [
              -71.0595626,
              42.3596165
            ],
            [
              -71.0595046,
              42.3596172
            ],
            [
              -71.0594502,
              42.3596304
            ],
            [
              -71.0593949,
              42.3596614
            ],
            [
              -71.0588596,
              42.3601567
            ],
            [
              -71.0585487,
              42.3604444
            ],
            [
              -71.0584802,
              42.3605156
            ],
            [
              -71.0580072,
              42.3610704
            ],
            [
              -71.057962,
              42.3611337
            ],
            [
              -71.0579284,
              42.3612009
            ],
            [
              -71.0579069,
              42.3612708
            ],
            [
              -71.057898,
              42.3613421
            ],
            [
              -71.0578932,
              42.3614833
            ],
            [
              -71.0578896,
              42.3615896
            ],
            [
              -71.057899,
              42.3616467
            ],
            [
              -71.0633783,
              42.3660352
            ],
            [
              -71.0643182,
              42.3656658
            ],
            [
              -71.0653387,
              42.3611528
            ],
            [
              -71.0653374,
              42.3611204
            ],
            [
              -71.0596096,
              42.3596257
            ],
            [
              -71.0595626,
              42.3596165
            ]
          ]
        ]
      }
    },
    {
      "type": "Feature",
      "properties": {
        "id": 5,
        "name": "B&A Eastbound",
        "pointCount": 1236
      },
      "geometry": {
        "type": "Polygon",
        "coordinates": [
          [
            [
              -71.070148,
              42.3722769
            ],
            [
              -71.0688377,
              42.3732238
            ],
            [
              -71.077099,
              42.3832232
            ],
            [
              -71.0890107,
              42.3819901
            ],
            [
              -71.0847635,
              42.3752898
            ],
            [
              -71.0804385,
              42.3741603
            ],
            [
              -71.070148,
              42.3722769
            ]
          ]
        ]
      }
    },
    {
      "type": "Feature",
      "properties": {
        "id": 6,
        "name": "Valley Track",
        "pointCount": 24
      },
      "geometry": {
        "type": "Polygon",
        "coordinates": [
          [
            [
              -71.0773642,
              42.3790754
            ],
            [
              -71.0773601,
              42.3790991
            ],
            [
              -71.0771624,
              42.3806555
            ],
            [
              -71.077152,
              42.3807988
            ],
            [
              -71.0770786,
              42.3844916
            ],
            [
              -71.0770969,
              42.3859563
            ],
            [
              -71.0771501,
              42.3860337
            ],
            [
              -71.0773642,
              42.3790754
            ]
          ]
        ]
      }
    },
    {
      "type": "Feature",
      "properties": {
        "id": 7,
        "name": "Yard 10 Lead",
        "pointCount": 24
      },
      "geometry": {
        "type": "Polygon",
        "coordinates": [
          [
            [
              -71.0953782,
              42.3774207
            ],
            [
              -71.0952776,
              42.3775733
            ],
            [
              -71.0957115,
              42.3778868
            ],
            [
              -71.098539,
              42.3793462
            ],
            [
              -71.0987779,
              42.3793217
            ],
            [
              -71.0969538,
              42.3782707
            ],
            [
              -71.0960908,
              42.3778022
            ],
            [
              -71.0953782,
              42.3774207
            ]
          ]
        ]
      }
    },
    {
      "type": "Feature",
      "properties": {
        "id": 8,
        "name": "4th Iron",
        "pointCount": 42
      },
      "geometry": {
        "type": "Polygon",
        "coordinates": [
          [
            [
              -71.0643871,
              42.3656981
            ],
            [
              -71.0641804,
              42.3657232
            ],
            [
              -71.0639942,
              42.3657751
            ],
            [
              -71.0635052,
              42.3659208
            ],
            [
              -71.0617764,
              42.3665199
            ],
            [
              -71.0618709,
              42.3665452
            ],
            [
              -71.061971,
              42.3665623
            ],
            [
              -71.0620726,
              42.3665702
            ],
            [
              -71.062173,
              42.366569
            ],
            [
              -71.0622755,
              42.3665585
            ],
            [
              -71.0623625,
              42.3665419
            ],
            [
              -71.0628243,
              42.3664349
            ],
            [
              -71.0647749,
              42.3657356
            ],
            [
              -71.0646093,
              42.3657059
            ],
            [
              -71.0643871,
              42.3656981
            ]
          ]
        ]
      }
    },
    {
      "type": "Feature",
      "properties": {
        "id": 9,
        "name": "MBTA Boston Engine Terminal",
        "pointCount": 112
      },
      "geometry": {
        "type": "Polygon",
        "coordinates": [
          [
            [
              -71.1668506,
              42.3400912
            ],
            [
              -71.1667296,
              42.3401084
            ],
            [
              -71.16671,
              42.3401276
            ],
            [
              -71.1670221,
              42.3408909
            ],
            [
              -71.1670631,
              42.34093
            ],
            [
              -71.1671771,
              42.3409697
            ],
            [
              -71.1675049,
              42.3410329
            ],
            [
              -71.1676849,
              42.3410556
            ],
            [
              -71.1677865,
              42.3410296
            ],
            [
              -71.1678525,
              42.3409614
            ],
            [
              -71.1678816,
              42.3408639
            ],
            [
              -71.1678659,
              42.3407778
            ],
            [
              -71.1672609,
              42.3402607
            ],
            [
              -71.1671986,
              42.3402121
            ],
            [
              -71.1671101,
              42.340171
            ],
            [
              -71.167052,
              42.3401531
            ],
            [
              -71.1668506,
              42.3400912
            ]
          ]
        ]
      }
    },
    {
      "type": "Feature",
      "properties": {
        "id": 10,
        "name": "MBTA Reservoir Yard",
        "pointCount": 10
      },
      "geometry": {
        "type": "Polygon",
        "coordinates": [
          [
            [
              -71.1008561,
              42.3493449
            ],
            [
              -71.1034081,
              42.349638
            ],
            [
              -71.1031975,
              42.3495985
            ],
            [
              -71.1027081,
              42.349511
            ],
            [
              -71.1011818,
              42.3493543
            ],
            [
              -71.1008561,
              42.3493449
            ]
          ]
        ]
      }
    },
    {
      "type": "Feature",
      "properties": {
        "id": 11,
        "name": "Green Line (Chestnut Hill Avenue)",
        "pointCount": 6
      },
      "geometry": {
        "type": "Polygon",
        "coordinates": [
          [
            [
              -71.0921088,
              42.3390774
            ],
            [
              -71.0919722,
              42.3391075
            ],
            [
              -71.0918697,
              42.3391356
            ],
            [
              -71.0910779,
              42.3394525
            ],
            [
              -71.0909825,
              42.339504
            ],
            [
              -71.090878,
              42.3395635
            ],
            [
              -71.0921088,
              42.3390774
            ]
          ]
        ]
      }
    },
    {
      "type": "Feature",
      "properties": {
        "id": 12,
        "name": "5",
        "pointCount": 33
      },
      "geometry": {
        "type": "Polygon",
        "coordinates": [
          [
            [
              -71.1105642,
              42.3281897
            ],
            [
              -71.110527,
              42.3281909
            ],
            [
              -71.1104948,
              42.3281973
            ],
            [
              -71.1104596,
              42.3282061
            ],
            [
              -71.1102021,
              42.3282858
            ],
            [
              -71.1101752,
              42.3282968
            ],
            [
              -71.1101512,
              42.3283097
            ],
            [
              -71.1101297,
              42.3283289
            ],
            [
              -71.110112,
              42.3283492
            ],
            [
              -71.1100971,
              42.3283722
            ],
            [
              -71.1100888,
              42.3283927
            ],
            [
              -71.1100816,
              42.3284262
            ],
            [
              -71.1100819,
              42.328447
            ],
            [
              -71.1100846,
              42.3284675
            ],
            [
              -71.1100923,
              42.3284902
            ],
            [
              -71.1101058,
              42.328513
            ],
            [
              -71.1101158,
              42.3285242
            ],
            [
              -71.1101308,
              42.3285406
            ],
            [
              -71.1101636,
              42.3285644
            ],
            [
              -71.110274,
              42.3286393
            ],
            [
              -71.1107396,
              42.3284532
            ],
            [
              -71.1107484,
              42.3283467
            ],
            [
              -71.1107491,
              42.3283376
            ],
            [
              -71.1107488,
              42.3283153
            ],
            [
              -71.1107453,
              42.328301
            ],
            [
              -71.110743,
              42.3282919
            ],
            [
              -71.1107312,
              42.3282677
            ],
            [
              -71.1107145,
              42.3282507
            ],
            [
              -71.1106728,
              42.3282214
            ],
            [
              -71.1106458,
              42.3282045
            ],
            [
              -71.1106021,
              42.3281938
            ],
            [
              -71.1105642,
              42.3281897
            ]
          ]
        ]
      }
    },
    {
      "type": "Feature",
      "properties": {
        "id": 13,
        "name": "3",
        "pointCount": 3
      },
      "geometry": {
        "type": "Polygon",
        "coordinates": [
          [
            [
              -71.0679566,
              42.3525646
            ],
            [
              -71.0671168,
              42.3526008
            ],
            [
              -71.0673145,
              42.3525948
            ],
            [
              -71.0679566,
              42.3525646
            ]
          ]
        ]
      }
    }
  ]
}